{
  "atendimento-assunto": [
    {
      "id": 1,
      "nome": "Folha de pagamento"
    },
    {
      "id": 2,
      "nome": "Nota fiscal"
    }
  ],
  "cidades": [
    {
      "nome": "Icara",
      "estado": "Acre",
      "id": 1
    },
    {
      "nome": "Criciuma",
      "estado": "Acre",
      "id": 2
    },
    {
      "nome": "Bahia",
      "estado": "Bahia",
      "id": 3
    }
  ],
  "departamento": [
    {
      "id": 1,
      "nome": "Fiscal"
    },
    {
      "id": 2,
      "nome": "Pessoal"
    }
  ],
  "atendimento-meio": [
    {
      "nome": "Telefones",
      "id": 1
    },
    {
      "id": 2,
      "nome": "Pessoalmente"
    },
    {
      "nome": "email",
      "id": 3
    }
  ],
  "pessoa": [
    {
      "id": 1,
      "nome": "PJ do Escritório",
      "email": "meu.escritorio@gmail.com",
      "tipo_pessoa": "PJ",
      "documento": "000010010000101",
      "endereco": "rua x, 0010",
      "telefone": "4834321111",
      "cidade": {
        "id": 1,
        "nome": "ICARA",
        "estado": "SC"
      },
      "ativo": true,
      "cliente": false,
      "departamento": null,
      "pessoa": null
    },
    {
      "nome": "José - Atendente do escritório",
      "tipo": "Pessoa física",
      "documento": "00100100101",
      "endereco": "rua a, 001",
      "telefone": "4834321111",
      "ativo": true,
      "cliente": false,
      "cidade": {
        "id": 1,
        "nome": "ICARA",
        "estado": "SC"
      },
      "departamento": {
        "id": 1,
        "nome": "FISCAL"
      },
      "pessoa": 1,
      "id": 2
    },
    {
      "nome": "PJ do Cliente A",
      "tipo": "Pessoa física",
      "documento": "12817412990",
      "endereco": "rua xZ, 0020",
      "telefone": "48343222222",
      "ativo": true,
      "cliente": false,
      "cidade": {
        "id": 1,
        "nome": "Icara",
        "estado": "SC"
      },
      "departamento": {
        "id": 1,
        "nome": "Fiscal"
      },
      "pessoa": {
        "id": 3,
        "nome": "PJ do Cliente A",
        "email": "cliente.a@gmail.com",
        "tipo_pessoa": "PJ",
        "documento": "000020020000202",
        "endereco": "rua xZ, 0020",
        "telefone": "48343222222",
        "cidade": {
          "id": 2,
          "nome": "CRICIUMA",
          "estado": "SC"
        },
        "ativo": true,
        "cliente": true,
        "departamento": null,
        "pessoa": null
      },
      "id": 3
    }
  ],
  "usuario": [
    {
      "nome": "user_fiscal",
      "email": "email@gmail.com",
      "pessoa": 2,
      "dataCadastro": "2023-11-26T18:19:43.062Z",
      "dataAtualizacao": "2023-11-26T18:19:43.062Z",
      "dataUltimoAcesso": "2023-11-26T18:19:43.062Z",
      "ativo": true,
      "administrador": null,
      "id": 1
    },
    {
      "nome": "user_pessoal",
      "email": "email@gmail.com",
      "pessoa": 3,
      "dataCadastro": "2023-11-26T18:19:29.755Z",
      "dataAtualizacao": "2023-11-26T18:19:29.755Z",
      "dataUltimoAcesso": "2023-11-26T18:19:29.756Z",
      "ativo": true,
      "administrador": null,
      "id": 2
    }
  ],
  "atendimento": [
    {
      "detalhes": "maria perguntou sobre como emitir nota fiscal",
      "assunto": {
        "id": 1,
        "nome": "Folha de pagamento"
      },
      "meio": {
        "id": 3,
        "nome": "E-MAIL"
      },
      "inicioAtendimento": null,
      "fimAtendimento": null,
      "solicitante": 1,
      "atendente": 2,
      "id": 1
    },
    {
      "detalhes": "joao",
      "assunto": {
        "id": 1,
        "nome": "Folha de pagamento"
      },
      "meio": 1,
      "inicioAtendimento": "2023-11-28T16:05:00",
      "fimAtendimento": "2023-11-30T15:04:00",
      "solicitante": 2,
      "atendente": 2,
      "id": 2
    }
  ]
}